cloudshell/__init__.py
cloudshell/nvidia/__init__.py
cloudshell/nvidia/onyx/__init__.py
cloudshell/nvidia/onyx/nvidia_constants.py
cloudshell/nvidia/onyx/cli/__init__.py
cloudshell/nvidia/onyx/cli/nvidia_cli_handler.py
cloudshell/nvidia/onyx/cli/nvidia_command_modes.py
cloudshell/nvidia/onyx/command_actions/__init__.py
cloudshell/nvidia/onyx/command_actions/add_remove_vlan_actions.py
cloudshell/nvidia/onyx/command_actions/enable_disable_snmp_actions.py
cloudshell/nvidia/onyx/command_actions/iface_actions.py
cloudshell/nvidia/onyx/command_actions/system_actions.py
cloudshell/nvidia/onyx/command_templates/__init__.py
cloudshell/nvidia/onyx/command_templates/add_remove_vlan.py
cloudshell/nvidia/onyx/command_templates/configuration.py
cloudshell/nvidia/onyx/command_templates/enable_disable_snmp.py
cloudshell/nvidia/onyx/command_templates/firmware.py
cloudshell/nvidia/onyx/command_templates/iface.py
cloudshell/nvidia/onyx/flows/__init__.py
cloudshell/nvidia/onyx/flows/nvidia_autoload_flow.py
cloudshell/nvidia/onyx/flows/nvidia_configuration_flow.py
cloudshell/nvidia/onyx/flows/nvidia_connectivity_flow.py
cloudshell/nvidia/onyx/flows/nvidia_disable_snmp_flow.py
cloudshell/nvidia/onyx/flows/nvidia_enable_snmp_flow.py
cloudshell/nvidia/onyx/flows/nvidia_run_command_flow.py
cloudshell/nvidia/onyx/flows/nvidia_state_flow.py
cloudshell/nvidia/onyx/helpers/__init__.py
cloudshell/nvidia/onyx/helpers/exceptions.py
cloudshell/nvidia/onyx/mibs/MELLANOX-PRODUCTS-MIB.py
cloudshell/nvidia/onyx/mibs/MELLANOX-SMI-MIB.py
cloudshell/nvidia/onyx/mibs/__init__.py
cloudshell/nvidia/onyx/sessions/__init__.py
cloudshell/nvidia/onyx/sessions/console_ssh_session.py
cloudshell/nvidia/onyx/sessions/console_telnet_session.py
cloudshell/nvidia/onyx/snmp/__init__.py
cloudshell/nvidia/onyx/snmp/nvidia_snmp_handler.py
tests/__init__.py
tests/cloudshell/__init__.py
tests/cloudshell/nvidia/__init__.py
tests/cloudshell/nvidia/cli/__init__.py
tests/cloudshell/nvidia/cli/test_cli_handler.py
cloudshell_nvidia_onyx-1.0.0.dist-info/METADATA
cloudshell_nvidia_onyx-1.0.0.dist-info/WHEEL
cloudshell_nvidia_onyx-1.0.0.dist-info/top_level.txt
cloudshell_nvidia_onyx-1.0.0.dist-info/RECORD
