Metadata-Version: 2.1
Name: cloudshell-nvidia-onyx
Version: 1.0.0
Summary: <your package description>
Home-page: http://www.qualisystems.com/
Author: QualiSystems
Author-email: info@qualisystems.com
License: UNKNOWN
Platform: UNKNOWN
Requires-Python: ~=3.7
Requires-Dist: cloudshell-cli (<5.0,>=4.0)
Requires-Dist: cloudshell-shell-flows (<2.0,>=1.0)
Requires-Dist: cloudshell-shell-connectivity-flow (<4.0,>=3.0)
Requires-Dist: cloudshell-snmp (<5.0,>=4.0)
Requires-Dist: cloudshell-snmp-autoload (<2.0,>=1.0)
